streamlit_simple_gallery/__init__.py
streamlit_simple_gallery-0.0.4.dist-info/LICENSE
streamlit_simple_gallery-0.0.4.dist-info/METADATA
streamlit_simple_gallery-0.0.4.dist-info/WHEEL
streamlit_simple_gallery-0.0.4.dist-info/top_level.txt
streamlit_simple_gallery-0.0.4.dist-info/RECORD
