Metadata-Version: 2.1
Name: streamlit-simple-gallery
Version: 0.0.4
Summary: Simple gallery for use in Streamlit projects.
Author-email: Michael Haslam <hreikin@gmail.com>
License: MIT License
Project-URL: Homepage, https://github.com/hreikin/streamlit-simple-gallery
Project-URL: Bug Tracker, https://github.com/hreikin/streamlit-simple-gallery/issues
Classifier: Programming Language :: Python :: 3
Classifier: License :: OSI Approved :: MIT License
Classifier: Operating System :: OS Independent
Requires-Python: >=3.7
License-File: LICENSE
Requires-Dist: streamlit (>=1.19.0)
